lazy_spider/__init__.py
lazy_spider/cache.py
lazy_spider/exception.py
lazy_spider/generic/__init__.py
lazy_spider/generic/proxy.py
lazy_spider/generic/spider/__init__.py
lazy_spider/generic/spider/spider.py
lazy_spider/http.py
lazy_spider/item.py
lazy_spider/parse/__init__.py
lazy_spider/parse/fonttools.py
lazy_spider/parse/parse.py
lazy_spider/spider.py
lazy_spider/template.py
lazy_spider/templates/general_template.py
lazy_spider/tools/__init__.py
lazy_spider/tools/proxy_collector.py
lazy_spider/typing.py
lazy_spider/utils/__init__.py
lazy_spider/utils/utils.py
lazy_spider-0.2.0.dist-info/LICENSE
lazy_spider-0.2.0.dist-info/WHEEL
lazy_spider-0.2.0.dist-info/METADATA
lazy_spider-0.2.0.dist-info/RECORD
